{
    "count": 512,
    "next": "https://nba-stats-db.herokuapp.com/api/playerdata/season/2010/?page=5",
    "previous": "https://nba-stats-db.herokuapp.com/api/playerdata/season/2010/?page=3",
    "results": [
        {
            "AST": 125,
            "BLK": 22,
            "DRB": 156,
            "ORB": 18,
            "PF": 101,
            "PTS": 649,
            "STL": 65,
            "TOV": 70,
            "TRB": 174,
            "age": 30,
            "effect_fg_percent": "0.486",
            "field_attempts": 548,
            "field_goals": 230,
            "field_percent": "0.420",
            "ft": 116,
            "ft_percent": "0.789",
            "fta": 147,
            "games": 51,
            "games_started": 28,
            "id": 7842,
            "minutes_played": 1695,
            "player_name": "John Salmons",
            "season": 2010,
            "team": "CHI",
            "three_attempts": 192,
            "three_fg": 73,
            "three_percent": "0.380",
            "two_attempts": 356,
            "two_fg": 157,
            "two_percent": "0.441"
        },
        {
            "AST": 89,
            "BLK": 2,
            "DRB": 69,
            "ORB": 9,
            "PF": 68,
            "PTS": 344,
            "STL": 29,
            "TOV": 50,
            "TRB": 78,
            "age": 30,
            "effect_fg_percent": "0.396",
            "field_attempts": 381,
            "field_goals": 132,
            "field_percent": "0.346",
            "ft": 42,
            "ft_percent": "0.933",
            "fta": 45,
            "games": 63,
            "games_started": 5,
            "id": 7843,
            "minutes_played": 829,
            "player_name": "Jannero Pargo",
            "season": 2010,
            "team": "CHI",
            "three_attempts": 138,
            "three_fg": 38,
            "three_percent": "0.275",
            "two_attempts": 243,
            "two_fg": 94,
            "two_percent": "0.387"
        },
        {
            "AST": 48,
            "BLK": 43,
            "DRB": 94,
            "ORB": 34,
            "PF": 126,
            "PTS": 256,
            "STL": 21,
            "TOV": 62,
            "TRB": 128,
            "age": 22,
            "effect_fg_percent": "0.488",
            "field_attempts": 210,
            "field_goals": 95,
            "field_percent": "0.452",
            "ft": 51,
            "ft_percent": "0.729",
            "fta": 70,
            "games": 65,
            "games_started": 11,
            "id": 7844,
            "minutes_played": 757,
            "player_name": "James Johnson",
            "season": 2010,
            "team": "CHI",
            "three_attempts": 46,
            "three_fg": 15,
            "three_percent": "0.326",
            "two_attempts": 164,
            "two_fg": 80,
            "two_percent": "0.488"
        },
        {
            "AST": 51,
            "BLK": 4,
            "DRB": 72,
            "ORB": 13,
            "PF": 49,
            "PTS": 292,
            "STL": 18,
            "TOV": 26,
            "TRB": 85,
            "age": 30,
            "effect_fg_percent": "0.449",
            "field_attempts": 272,
            "field_goals": 108,
            "field_percent": "0.397",
            "ft": 48,
            "ft_percent": "0.762",
            "fta": 63,
            "games": 29,
            "games_started": 1,
            "id": 7845,
            "minutes_played": 680,
            "player_name": "Ronald Murray",
            "season": 2010,
            "team": "CHI",
            "three_attempts": 90,
            "three_fg": 28,
            "three_percent": "0.311",
            "two_attempts": 182,
            "two_fg": 80,
            "two_percent": "0.440"
        },
        {
            "AST": 33,
            "BLK": 48,
            "DRB": 141,
            "ORB": 42,
            "PF": 64,
            "PTS": 256,
            "STL": 40,
            "TOV": 52,
            "TRB": 183,
            "age": 23,
            "effect_fg_percent": "0.483",
            "field_attempts": 205,
            "field_goals": 99,
            "field_percent": "0.483",
            "ft": 58,
            "ft_percent": "0.644",
            "fta": 90,
            "games": 29,
            "games_started": 3,
            "id": 7846,
            "minutes_played": 678,
            "player_name": "Tyrus Thomas",
            "season": 2010,
            "team": "CHI",
            "three_attempts": 1,
            "three_fg": 0,
            "three_percent": "0.000",
            "two_attempts": 204,
            "two_fg": 99,
            "two_percent": "0.485"
        },
        {
            "AST": 17,
            "BLK": 8,
            "DRB": 62,
            "ORB": 40,
            "PF": 43,
            "PTS": 243,
            "STL": 7,
            "TOV": 23,
            "TRB": 102,
            "age": 27,
            "effect_fg_percent": "0.483",
            "field_attempts": 172,
            "field_goals": 83,
            "field_percent": "0.483",
            "ft": 77,
            "ft_percent": "0.755",
            "fta": 102,
            "games": 28,
            "games_started": 0,
            "id": 7847,
            "minutes_played": 533,
            "player_name": "Hakim Warrick",
            "season": 2010,
            "team": "CHI",
            "three_attempts": 1,
            "three_fg": 0,
            "three_percent": "0.000",
            "two_attempts": 171,
            "two_fg": 83,
            "two_percent": "0.485"
        },
        {
            "AST": 7,
            "BLK": 4,
            "DRB": 40,
            "ORB": 19,
            "PF": 50,
            "PTS": 37,
            "STL": 8,
            "TOV": 14,
            "TRB": 59,
            "age": 25,
            "effect_fg_percent": "0.517",
            "field_attempts": 29,
            "field_goals": 15,
            "field_percent": "0.517",
            "ft": 7,
            "ft_percent": "0.636",
            "fta": 11,
            "games": 18,
            "games_started": 0,
            "id": 7848,
            "minutes_played": 224,
            "player_name": "Chris Richard",
            "season": 2010,
            "team": "CHI",
            "three_attempts": 0,
            "three_fg": 0,
            "three_percent": null,
            "two_attempts": 29,
            "two_fg": 15,
            "two_percent": "0.517"
        },
        {
            "AST": 16,
            "BLK": 0,
            "DRB": 11,
            "ORB": 3,
            "PF": 8,
            "PTS": 66,
            "STL": 4,
            "TOV": 12,
            "TRB": 14,
            "age": 25,
            "effect_fg_percent": "0.511",
            "field_attempts": 45,
            "field_goals": 21,
            "field_percent": "0.467",
            "ft": 20,
            "ft_percent": "0.741",
            "fta": 27,
            "games": 12,
            "games_started": 1,
            "id": 7849,
            "minutes_played": 135,
            "player_name": "Acie Law",
            "season": 2010,
            "team": "CHI",
            "three_attempts": 12,
            "three_fg": 4,
            "three_percent": "0.333",
            "two_attempts": 33,
            "two_fg": 17,
            "two_percent": "0.515"
        },
        {
            "AST": 9,
            "BLK": 0,
            "DRB": 13,
            "ORB": 1,
            "PF": 12,
            "PTS": 13,
            "STL": 1,
            "TOV": 4,
            "TRB": 14,
            "age": 39,
            "effect_fg_percent": "0.183",
            "field_attempts": 30,
            "field_goals": 5,
            "field_percent": "0.167",
            "ft": 2,
            "ft_percent": "1.000",
            "fta": 2,
            "games": 13,
            "games_started": 0,
            "id": 7850,
            "minutes_played": 122,
            "player_name": "Lindsey Hunter",
            "season": 2010,
            "team": "CHI",
            "three_attempts": 13,
            "three_fg": 1,
            "three_percent": "0.077",
            "two_attempts": 17,
            "two_fg": 4,
            "two_percent": "0.235"
        },
        {
            "AST": 7,
            "BLK": 1,
            "DRB": 13,
            "ORB": 2,
            "PF": 10,
            "PTS": 20,
            "STL": 3,
            "TOV": 5,
            "TRB": 15,
            "age": 31,
            "effect_fg_percent": "0.278",
            "field_attempts": 36,
            "field_goals": 8,
            "field_percent": "0.222",
            "ft": 0,
            "ft_percent": null,
            "fta": 0,
            "games": 11,
            "games_started": 0,
            "id": 7851,
            "minutes_played": 93,
            "player_name": "Devin Brown",
            "season": 2010,
            "team": "CHI",
            "three_attempts": 17,
            "three_fg": 4,
            "three_percent": "0.235",
            "two_attempts": 19,
            "two_fg": 4,
            "two_percent": "0.211"
        },
        {
            "AST": 2,
            "BLK": 0,
            "DRB": 11,
            "ORB": 5,
            "PF": 10,
            "PTS": 18,
            "STL": 0,
            "TOV": 1,
            "TRB": 16,
            "age": 25,
            "effect_fg_percent": "0.381",
            "field_attempts": 21,
            "field_goals": 8,
            "field_percent": "0.381",
            "ft": 2,
            "ft_percent": "0.286",
            "fta": 7,
            "games": 8,
            "games_started": 0,
            "id": 7852,
            "minutes_played": 50,
            "player_name": "Aaron Gray",
            "season": 2010,
            "team": "CHI",
            "three_attempts": 0,
            "three_fg": 0,
            "three_percent": null,
            "two_attempts": 21,
            "two_fg": 8,
            "two_percent": "0.381"
        },
        {
            "AST": 2,
            "BLK": 1,
            "DRB": 3,
            "ORB": 2,
            "PF": 9,
            "PTS": 4,
            "STL": 1,
            "TOV": 0,
            "TRB": 5,
            "age": 23,
            "effect_fg_percent": "0.167",
            "field_attempts": 6,
            "field_goals": 1,
            "field_percent": "0.167",
            "ft": 2,
            "ft_percent": "0.667",
            "fta": 3,
            "games": 8,
            "games_started": 0,
            "id": 7853,
            "minutes_played": 29,
            "player_name": "Joe Alexander",
            "season": 2010,
            "team": "CHI",
            "three_attempts": 1,
            "three_fg": 0,
            "three_percent": "0.000",
            "two_attempts": 5,
            "two_fg": 1,
            "two_percent": "0.200"
        },
        {
            "AST": 112,
            "BLK": 65,
            "DRB": 305,
            "ORB": 41,
            "PF": 159,
            "PTS": 774,
            "STL": 56,
            "TOV": 93,
            "TRB": 346,
            "age": 24,
            "effect_fg_percent": "0.511",
            "field_attempts": 702,
            "field_goals": 297,
            "field_percent": "0.423",
            "ft": 56,
            "ft_percent": "0.629",
            "fta": 89,
            "games": 82,
            "games_started": 64,
            "id": 7854,
            "minutes_played": 2491,
            "player_name": "Brandon Rush",
            "season": 2010,
            "team": "IND",
            "three_attempts": 302,
            "three_fg": 124,
            "three_percent": "0.411",
            "two_attempts": 400,
            "two_fg": 173,
            "two_percent": "0.433"
        },
        {
            "AST": 150,
            "BLK": 34,
            "DRB": 608,
            "ORB": 129,
            "PF": 175,
            "PTS": 1050,
            "STL": 72,
            "TOV": 100,
            "TRB": 737,
            "age": 29,
            "effect_fg_percent": "0.551",
            "field_attempts": 813,
            "field_goals": 384,
            "field_percent": "0.472",
            "ft": 154,
            "ft_percent": "0.798",
            "fta": 193,
            "games": 72,
            "games_started": 69,
            "id": 7855,
            "minutes_played": 2344,
            "player_name": "Troy Murphy",
            "season": 2010,
            "team": "IND",
            "three_attempts": 333,
            "three_fg": 128,
            "three_percent": "0.384",
            "two_attempts": 480,
            "two_fg": 256,
            "two_percent": "0.533"
        },
        {
            "AST": 399,
            "BLK": 16,
            "DRB": 186,
            "ORB": 54,
            "PF": 181,
            "PTS": 619,
            "STL": 104,
            "TOV": 175,
            "TRB": 240,
            "age": 30,
            "effect_fg_percent": "0.476",
            "field_attempts": 524,
            "field_goals": 223,
            "field_percent": "0.426",
            "ft": 120,
            "ft_percent": "0.710",
            "fta": 169,
            "games": 79,
            "games_started": 52,
            "id": 7856,
            "minutes_played": 2322,
            "player_name": "Earl Watson",
            "season": 2010,
            "team": "IND",
            "three_attempts": 184,
            "three_fg": 53,
            "three_percent": "0.288",
            "two_attempts": 340,
            "two_fg": 170,
            "two_percent": "0.500"
        },
        {
            "AST": 171,
            "BLK": 51,
            "DRB": 275,
            "ORB": 67,
            "PF": 183,
            "PTS": 1497,
            "STL": 94,
            "TOV": 157,
            "TRB": 342,
            "age": 26,
            "effect_fg_percent": "0.498",
            "field_attempts": 1139,
            "field_goals": 488,
            "field_percent": "0.428",
            "ft": 363,
            "ft_percent": "0.848",
            "fta": 428,
            "games": 62,
            "games_started": 62,
            "id": 7857,
            "minutes_played": 2278,
            "player_name": "Danny Granger",
            "season": 2010,
            "team": "IND",
            "three_attempts": 438,
            "three_fg": 158,
            "three_percent": "0.361",
            "two_attempts": 701,
            "two_fg": 330,
            "two_percent": "0.471"
        },
        {
            "AST": 158,
            "BLK": 131,
            "DRB": 287,
            "ORB": 177,
            "PF": 285,
            "PTS": 946,
            "STL": 30,
            "TOV": 145,
            "TRB": 464,
            "age": 23,
            "effect_fg_percent": "0.497",
            "field_attempts": 782,
            "field_goals": 387,
            "field_percent": "0.495",
            "ft": 169,
            "ft_percent": "0.754",
            "fta": 224,
            "games": 81,
            "games_started": 69,
            "id": 7858,
            "minutes_played": 2035,
            "player_name": "Roy Hibbert",
            "season": 2010,
            "team": "IND",
            "three_attempts": 6,
            "three_fg": 3,
            "three_percent": "0.500",
            "two_attempts": 776,
            "two_fg": 384,
            "two_percent": "0.495"
        },
        {
            "AST": 150,
            "BLK": 39,
            "DRB": 181,
            "ORB": 48,
            "PF": 237,
            "PTS": 776,
            "STL": 40,
            "TOV": 129,
            "TRB": 229,
            "age": 29,
            "effect_fg_percent": "0.464",
            "field_attempts": 623,
            "field_goals": 287,
            "field_percent": "0.461",
            "ft": 198,
            "ft_percent": "0.770",
            "fta": 257,
            "games": 76,
            "games_started": 26,
            "id": 7859,
            "minutes_played": 1892,
            "player_name": "Dahntay Jones",
            "season": 2010,
            "team": "IND",
            "three_attempts": 32,
            "three_fg": 4,
            "three_percent": "0.125",
            "two_attempts": 591,
            "two_fg": 283,
            "two_percent": "0.479"
        },
        {
            "AST": 103,
            "BLK": 15,
            "DRB": 211,
            "ORB": 25,
            "PF": 105,
            "PTS": 666,
            "STL": 38,
            "TOV": 72,
            "TRB": 236,
            "age": 29,
            "effect_fg_percent": "0.478",
            "field_attempts": 558,
            "field_goals": 229,
            "field_percent": "0.410",
            "ft": 133,
            "ft_percent": "0.842",
            "fta": 158,
            "games": 67,
            "games_started": 15,
            "id": 7860,
            "minutes_played": 1486,
            "player_name": "Mike Dunleavy",
            "season": 2010,
            "team": "IND",
            "three_attempts": 236,
            "three_fg": 75,
            "three_percent": "0.318",
            "two_attempts": 322,
            "two_fg": 154,
            "two_percent": "0.478"
        },
        {
            "AST": 180,
            "BLK": 11,
            "DRB": 108,
            "ORB": 41,
            "PF": 102,
            "PTS": 484,
            "STL": 44,
            "TOV": 90,
            "TRB": 149,
            "age": 26,
            "effect_fg_percent": "0.455",
            "field_attempts": 418,
            "field_goals": 186,
            "field_percent": "0.445",
            "ft": 104,
            "ft_percent": "0.770",
            "fta": 135,
            "games": 47,
            "games_started": 32,
            "id": 7861,
            "minutes_played": 1189,
            "player_name": "T.J. Ford",
            "season": 2010,
            "team": "IND",
            "three_attempts": 50,
            "three_fg": 8,
            "three_percent": "0.160",
            "two_attempts": 368,
            "two_fg": 178,
            "two_percent": "0.484"
        },
        {
            "AST": 106,
            "BLK": 3,
            "DRB": 76,
            "ORB": 12,
            "PF": 53,
            "PTS": 410,
            "STL": 35,
            "TOV": 59,
            "TRB": 88,
            "age": 23,
            "effect_fg_percent": "0.494",
            "field_attempts": 354,
            "field_goals": 145,
            "field_percent": "0.410",
            "ft": 60,
            "ft_percent": "0.800",
            "fta": 75,
            "games": 56,
            "games_started": 2,
            "id": 7862,
            "minutes_played": 865,
            "player_name": "A.J. Price",
            "season": 2010,
            "team": "IND",
            "three_attempts": 174,
            "three_fg": 60,
            "three_percent": "0.345",
            "two_attempts": 180,
            "two_fg": 85,
            "two_percent": "0.472"
        },
        {
            "AST": 72,
            "BLK": 9,
            "DRB": 74,
            "ORB": 6,
            "PF": 53,
            "PTS": 357,
            "STL": 18,
            "TOV": 54,
            "TRB": 80,
            "age": 27,
            "effect_fg_percent": "0.497",
            "field_attempts": 311,
            "field_goals": 136,
            "field_percent": "0.437",
            "ft": 48,
            "ft_percent": "0.828",
            "fta": 58,
            "games": 47,
            "games_started": 10,
            "id": 7863,
            "minutes_played": 813,
            "player_name": "Luther Head",
            "season": 2010,
            "team": "IND",
            "three_attempts": 105,
            "three_fg": 37,
            "three_percent": "0.352",
            "two_attempts": 206,
            "two_fg": 99,
            "two_percent": "0.481"
        },
        {
            "AST": 32,
            "BLK": 37,
            "DRB": 93,
            "ORB": 51,
            "PF": 125,
            "PTS": 207,
            "STL": 14,
            "TOV": 40,
            "TRB": 144,
            "age": 25,
            "effect_fg_percent": "0.443",
            "field_attempts": 176,
            "field_goals": 78,
            "field_percent": "0.443",
            "ft": 51,
            "ft_percent": "0.718",
            "fta": 71,
            "games": 52,
            "games_started": 2,
            "id": 7864,
            "minutes_played": 675,
            "player_name": "Solomon Jones",
            "season": 2010,
            "team": "IND",
            "three_attempts": 3,
            "three_fg": 0,
            "three_percent": "0.000",
            "two_attempts": 173,
            "two_fg": 78,
            "two_percent": "0.451"
        },
        {
            "AST": 44,
            "BLK": 16,
            "DRB": 87,
            "ORB": 40,
            "PF": 74,
            "PTS": 179,
            "STL": 17,
            "TOV": 19,
            "TRB": 127,
            "age": 22,
            "effect_fg_percent": "0.548",
            "field_attempts": 146,
            "field_goals": 76,
            "field_percent": "0.521",
            "ft": 19,
            "ft_percent": "0.500",
            "fta": 38,
            "games": 42,
            "games_started": 3,
            "id": 7865,
            "minutes_played": 524,
            "player_name": "Josh McRoberts",
            "season": 2010,
            "team": "IND",
            "three_attempts": 23,
            "three_fg": 8,
            "three_percent": "0.348",
            "two_attempts": 123,
            "two_fg": 68,
            "two_percent": "0.553"
        },
        {
            "AST": 28,
            "BLK": 8,
            "DRB": 78,
            "ORB": 60,
            "PF": 70,
            "PTS": 246,
            "STL": 17,
            "TOV": 21,
            "TRB": 138,
            "age": 24,
            "effect_fg_percent": "0.360",
            "field_attempts": 225,
            "field_goals": 81,
            "field_percent": "0.360",
            "ft": 84,
            "ft_percent": "0.743",
            "fta": 113,
            "games": 29,
            "games_started": 1,
            "id": 7866,
            "minutes_played": 511,
            "player_name": "Tyler Hansbrough",
            "season": 2010,
            "team": "IND",
            "three_attempts": 4,
            "three_fg": 0,
            "three_percent": "0.000",
            "two_attempts": 221,
            "two_fg": 81,
            "two_percent": "0.367"
        },
        {
            "AST": 21,
            "BLK": 4,
            "DRB": 47,
            "ORB": 34,
            "PF": 45,
            "PTS": 49,
            "STL": 3,
            "TOV": 14,
            "TRB": 81,
            "age": 33,
            "effect_fg_percent": "0.478",
            "field_attempts": 46,
            "field_goals": 22,
            "field_percent": "0.478",
            "ft": 5,
            "ft_percent": "0.556",
            "fta": 9,
            "games": 16,
            "games_started": 3,
            "id": 7867,
            "minutes_played": 255,
            "player_name": "Jeff Foster",
            "season": 2010,
            "team": "IND",
            "three_attempts": 1,
            "three_fg": 0,
            "three_percent": "0.000",
            "two_attempts": 45,
            "two_fg": 22,
            "two_percent": "0.489"
        },
        {
            "AST": 4,
            "BLK": 0,
            "DRB": 2,
            "ORB": 0,
            "PF": 1,
            "PTS": 3,
            "STL": 3,
            "TOV": 0,
            "TRB": 2,
            "age": 27,
            "effect_fg_percent": "0.250",
            "field_attempts": 6,
            "field_goals": 1,
            "field_percent": "0.167",
            "ft": 0,
            "ft_percent": "0.000",
            "fta": 2,
            "games": 4,
            "games_started": 0,
            "id": 7868,
            "minutes_played": 25,
            "player_name": "Travis Diener",
            "season": 2010,
            "team": "IND",
            "three_attempts": 5,
            "three_fg": 1,
            "three_percent": "0.200",
            "two_attempts": 1,
            "two_fg": 0,
            "two_percent": "0.000"
        },
        {
            "AST": 348,
            "BLK": 12,
            "DRB": 214,
            "ORB": 67,
            "PF": 205,
            "PTS": 1215,
            "STL": 101,
            "TOV": 163,
            "TRB": 281,
            "age": 23,
            "effect_fg_percent": "0.413",
            "field_attempts": 1109,
            "field_goals": 449,
            "field_percent": "0.405",
            "ft": 299,
            "ft_percent": "0.833",
            "fta": 359,
            "games": 73,
            "games_started": 67,
            "id": 7869,
            "minutes_played": 2499,
            "player_name": "Rodney Stuckey",
            "season": 2010,
            "team": "DET",
            "three_attempts": 79,
            "three_fg": 18,
            "three_percent": "0.228",
            "two_attempts": 1030,
            "two_fg": 431,
            "two_percent": "0.418"
        },
        {
            "AST": 58,
            "BLK": 29,
            "DRB": 284,
            "ORB": 194,
            "PF": 230,
            "PTS": 741,
            "STL": 79,
            "TOV": 82,
            "TRB": 478,
            "age": 22,
            "effect_fg_percent": "0.511",
            "field_attempts": 603,
            "field_goals": 290,
            "field_percent": "0.481",
            "ft": 125,
            "ft_percent": "0.710",
            "fta": 176,
            "games": 80,
            "games_started": 73,
            "id": 7870,
            "minutes_played": 2232,
            "player_name": "Jonas Jerebko",
            "season": 2010,
            "team": "DET",
            "three_attempts": 115,
            "three_fg": 36,
            "three_percent": "0.313",
            "two_attempts": 488,
            "two_fg": 254,
            "two_percent": "0.520"
        },
        {
            "AST": 105,
            "BLK": 84,
            "DRB": 352,
            "ORB": 245,
            "PF": 131,
            "PTS": 381,
            "STL": 86,
            "TOV": 64,
            "TRB": 597,
            "age": 35,
            "effect_fg_percent": "0.541",
            "field_attempts": 292,
            "field_goals": 158,
            "field_percent": "0.541",
            "ft": 65,
            "ft_percent": "0.406",
            "fta": 160,
            "games": 69,
            "games_started": 67,
            "id": 7871,
            "minutes_played": 1975,
            "player_name": "Ben Wallace",
            "season": 2010,
            "team": "DET",
            "three_attempts": 2,
            "three_fg": 0,
            "three_percent": "0.000",
            "two_attempts": 290,
            "two_fg": 158,
            "two_percent": "0.545"
        },
        {
            "AST": 53,
            "BLK": 55,
            "DRB": 280,
            "ORB": 85,
            "PF": 223,
            "PTS": 931,
            "STL": 48,
            "TOV": 74,
            "TRB": 365,
            "age": 25,
            "effect_fg_percent": "0.499",
            "field_attempts": 827,
            "field_goals": 363,
            "field_percent": "0.439",
            "ft": 106,
            "ft_percent": "0.815",
            "fta": 130,
            "games": 78,
            "games_started": 16,
            "id": 7872,
            "minutes_played": 1848,
            "player_name": "Charlie Villanueva",
            "season": 2010,
            "team": "DET",
            "three_attempts": 282,
            "three_fg": 99,
            "three_percent": "0.351",
            "two_attempts": 545,
            "two_fg": 264,
            "two_percent": "0.484"
        },
        {
            "AST": 166,
            "BLK": 6,
            "DRB": 93,
            "ORB": 26,
            "PF": 147,
            "PTS": 855,
            "STL": 49,
            "TOV": 118,
            "TRB": 119,
            "age": 26,
            "effect_fg_percent": "0.470",
            "field_attempts": 699,
            "field_goals": 291,
            "field_percent": "0.416",
            "ft": 198,
            "ft_percent": "0.861",
            "fta": 230,
            "games": 62,
            "games_started": 17,
            "id": 7873,
            "minutes_played": 1730,
            "player_name": "Ben Gordon",
            "season": 2010,
            "team": "DET",
            "three_attempts": 234,
            "three_fg": 75,
            "three_percent": "0.321",
            "two_attempts": 465,
            "two_fg": 216,
            "two_percent": "0.465"
        },
        {
            "AST": 283,
            "BLK": 7,
            "DRB": 118,
            "ORB": 24,
            "PF": 143,
            "PTS": 628,
            "STL": 55,
            "TOV": 115,
            "TRB": 142,
            "age": 27,
            "effect_fg_percent": "0.455",
            "field_attempts": 534,
            "field_goals": 237,
            "field_percent": "0.444",
            "ft": 142,
            "ft_percent": "0.798",
            "fta": 178,
            "games": 63,
            "games_started": 20,
            "id": 7874,
            "minutes_played": 1667,
            "player_name": "Will Bynum",
            "season": 2010,
            "team": "DET",
            "three_attempts": 55,
            "three_fg": 12,
            "three_percent": "0.218",
            "two_attempts": 479,
            "two_fg": 225,
            "two_percent": "0.470"
        },
        {
            "AST": 161,
            "BLK": 22,
            "DRB": 177,
            "ORB": 71,
            "PF": 77,
            "PTS": 661,
            "STL": 34,
            "TOV": 60,
            "TRB": 248,
            "age": 29,
            "effect_fg_percent": "0.509",
            "field_attempts": 580,
            "field_goals": 282,
            "field_percent": "0.486",
            "ft": 70,
            "ft_percent": "0.714",
            "fta": 98,
            "games": 49,
            "games_started": 49,
            "id": 7875,
            "minutes_played": 1664,
            "player_name": "Tayshaun Prince",
            "season": 2010,
            "team": "DET",
            "three_attempts": 73,
            "three_fg": 27,
            "three_percent": "0.370",
            "two_attempts": 507,
            "two_fg": 255,
            "two_percent": "0.503"
        },
        {
            "AST": 202,
            "BLK": 3,
            "DRB": 92,
            "ORB": 30,
            "PF": 115,
            "PTS": 831,
            "STL": 30,
            "TOV": 115,
            "TRB": 122,
            "age": 31,
            "effect_fg_percent": "0.437",
            "field_attempts": 717,
            "field_goals": 293,
            "field_percent": "0.409",
            "ft": 204,
            "ft_percent": "0.846",
            "fta": 241,
            "games": 46,
            "games_started": 46,
            "id": 7876,
            "minutes_played": 1552,
            "player_name": "Richard Hamilton",
            "season": 2010,
            "team": "DET",
            "three_attempts": 138,
            "three_fg": 41,
            "three_percent": "0.297",
            "two_attempts": 579,
            "two_fg": 252,
            "two_percent": "0.435"
        },
        {
            "AST": 39,
            "BLK": 38,
            "DRB": 240,
            "ORB": 161,
            "PF": 175,
            "PTS": 513,
            "STL": 36,
            "TOV": 68,
            "TRB": 401,
            "age": 26,
            "effect_fg_percent": "0.511",
            "field_attempts": 415,
            "field_goals": 212,
            "field_percent": "0.511",
            "ft": 89,
            "ft_percent": "0.574",
            "fta": 155,
            "games": 76,
            "games_started": 29,
            "id": 7877,
            "minutes_played": 1550,
            "player_name": "Jason Maxiell",
            "season": 2010,
            "team": "DET",
            "three_attempts": 1,
            "three_fg": 0,
            "three_percent": "0.000",
            "two_attempts": 414,
            "two_fg": 212,
            "two_percent": "0.512"
        },
        {
            "AST": 34,
            "BLK": 26,
            "DRB": 140,
            "ORB": 34,
            "PF": 114,
            "PTS": 349,
            "STL": 25,
            "TOV": 48,
            "TRB": 174,
            "age": 21,
            "effect_fg_percent": "0.514",
            "field_attempts": 295,
            "field_goals": 137,
            "field_percent": "0.464",
            "ft": 46,
            "ft_percent": "0.821",
            "fta": 56,
            "games": 69,
            "games_started": 4,
            "id": 7878,
            "minutes_played": 915,
            "player_name": "Austin Daye",
            "season": 2010,
            "team": "DET",
            "three_attempts": 95,
            "three_fg": 29,
            "three_percent": "0.305",
            "two_attempts": 200,
            "two_fg": 108,
            "two_percent": "0.540"
        },
        {
            "AST": 22,
            "BLK": 12,
            "DRB": 124,
            "ORB": 53,
            "PF": 93,
            "PTS": 157,
            "STL": 15,
            "TOV": 43,
            "TRB": 177,
            "age": 27,
            "effect_fg_percent": "0.500",
            "field_attempts": 124,
            "field_goals": 62,
            "field_percent": "0.500",
            "ft": 33,
            "ft_percent": "0.337",
            "fta": 98,
            "games": 48,
            "games_started": 1,
            "id": 7879,
            "minutes_played": 660,
            "player_name": "Kwame Brown",
            "season": 2010,
            "team": "DET",
            "three_attempts": 1,
            "three_fg": 0,
            "three_percent": "0.000",
            "two_attempts": 123,
            "two_fg": 62,
            "two_percent": "0.504"
        },
        {
            "AST": 91,
            "BLK": 0,
            "DRB": 24,
            "ORB": 5,
            "PF": 53,
            "PTS": 161,
            "STL": 17,
            "TOV": 32,
            "TRB": 29,
            "age": 35,
            "effect_fg_percent": "0.433",
            "field_attempts": 157,
            "field_goals": 57,
            "field_percent": "0.363",
            "ft": 25,
            "ft_percent": "0.926",
            "fta": 27,
            "games": 40,
            "games_started": 11,
            "id": 7880,
            "minutes_played": 644,
            "player_name": "Chucky Atkins",
            "season": 2010,
            "team": "DET",
            "three_attempts": 73,
            "three_fg": 22,
            "three_percent": "0.301",
            "two_attempts": 84,
            "two_fg": 35,
            "two_percent": "0.417"
        },
        {
            "AST": 13,
            "BLK": 12,
            "DRB": 73,
            "ORB": 44,
            "PF": 64,
            "PTS": 152,
            "STL": 13,
            "TOV": 38,
            "TRB": 117,
            "age": 27,
            "effect_fg_percent": "0.525",
            "field_attempts": 120,
            "field_goals": 63,
            "field_percent": "0.525",
            "ft": 26,
            "ft_percent": "0.500",
            "fta": 52,
            "games": 34,
            "games_started": 10,
            "id": 7881,
            "minutes_played": 441,
            "player_name": "Chris Wilcox",
            "season": 2010,
            "team": "DET",
            "three_attempts": 0,
            "three_fg": 0,
            "three_percent": null,
            "two_attempts": 120,
            "two_fg": 63,
            "two_percent": "0.525"
        },
        {
            "AST": 16,
            "BLK": 7,
            "DRB": 31,
            "ORB": 14,
            "PF": 52,
            "PTS": 134,
            "STL": 8,
            "TOV": 16,
            "TRB": 45,
            "age": 22,
            "effect_fg_percent": "0.412",
            "field_attempts": 130,
            "field_goals": 46,
            "field_percent": "0.354",
            "ft": 27,
            "ft_percent": "0.711",
            "fta": 38,
            "games": 44,
            "games_started": 0,
            "id": 7882,
            "minutes_played": 405,
            "player_name": "DaJuan Summers",
            "season": 2010,
            "team": "DET",
            "three_attempts": 42,
            "three_fg": 15,
            "three_percent": "0.357",
            "two_attempts": 88,
            "two_fg": 31,
            "two_percent": "0.352"
        },
        {
            "AST": 414,
            "BLK": 26,
            "DRB": 314,
            "ORB": 66,
            "PF": 204,
            "PTS": 1450,
            "STL": 109,
            "TOV": 216,
            "TRB": 380,
            "age": 20,
            "effect_fg_percent": "0.473",
            "field_attempts": 1165,
            "field_goals": 533,
            "field_percent": "0.458",
            "ft": 348,
            "ft_percent": "0.748",
            "fta": 465,
            "games": 72,
            "games_started": 72,
            "id": 7883,
            "minutes_played": 2677,
            "player_name": "Tyreke Evans",
            "season": 2010,
            "team": "SAC",
            "three_attempts": 141,
            "three_fg": 36,
            "three_percent": "0.255",
            "two_attempts": 1024,
            "two_fg": 497,
            "two_percent": "0.485"
        },
        {
            "AST": 372,
            "BLK": 10,
            "DRB": 181,
            "ORB": 38,
            "PF": 166,
            "PTS": 1023,
            "STL": 89,
            "TOV": 136,
            "TRB": 219,
            "age": 27,
            "effect_fg_percent": "0.538",
            "field_attempts": 841,
            "field_goals": 415,
            "field_percent": "0.493",
            "ft": 118,
            "ft_percent": "0.837",
            "fta": 141,
            "games": 79,
            "games_started": 41,
            "id": 7884,
            "minutes_played": 2477,
            "player_name": "Beno Udrih",
            "season": 2010,
            "team": "SAC",
            "three_attempts": 199,
            "three_fg": 75,
            "three_percent": "0.377",
            "two_attempts": 642,
            "two_fg": 340,
            "two_percent": "0.530"
        },
        {
            "AST": 124,
            "BLK": 73,
            "DRB": 413,
            "ORB": 224,
            "PF": 279,
            "PTS": 939,
            "STL": 41,
            "TOV": 139,
            "TRB": 637,
            "age": 23,
            "effect_fg_percent": "0.473",
            "field_attempts": 784,
            "field_goals": 370,
            "field_percent": "0.472",
            "ft": 198,
            "ft_percent": "0.715",
            "fta": 277,
            "games": 75,
            "games_started": 58,
            "id": 7885,
            "minutes_played": 2357,
            "player_name": "Jason Thompson",
            "season": 2010,
            "team": "SAC",
            "three_attempts": 10,
            "three_fg": 1,
            "three_percent": "0.100",
            "two_attempts": 774,
            "two_fg": 369,
            "two_percent": "0.477"
        },
        {
            "AST": 95,
            "BLK": 17,
            "DRB": 274,
            "ORB": 75,
            "PF": 125,
            "PTS": 792,
            "STL": 54,
            "TOV": 98,
            "TRB": 349,
            "age": 21,
            "effect_fg_percent": "0.502",
            "field_attempts": 672,
            "field_goals": 300,
            "field_percent": "0.446",
            "ft": 117,
            "ft_percent": "0.672",
            "fta": 174,
            "games": 77,
            "games_started": 31,
            "id": 7886,
            "minutes_played": 1931,
            "player_name": "Omri Casspi",
            "season": 2010,
            "team": "SAC",
            "three_attempts": 203,
            "three_fg": 75,
            "three_percent": "0.369",
            "two_attempts": 469,
            "two_fg": 225,
            "two_percent": "0.480"
        },
        {
            "AST": 158,
            "BLK": 83,
            "DRB": 291,
            "ORB": 145,
            "PF": 200,
            "PTS": 723,
            "STL": 32,
            "TOV": 131,
            "TRB": 436,
            "age": 21,
            "effect_fg_percent": "0.488",
            "field_attempts": 666,
            "field_goals": 312,
            "field_percent": "0.468",
            "ft": 73,
            "ft_percent": "0.689",
            "fta": 106,
            "games": 72,
            "games_started": 59,
            "id": 7887,
            "minutes_played": 1904,
            "player_name": "Spencer Hawes",
            "season": 2010,
            "team": "SAC",
            "three_attempts": 87,
            "three_fg": 26,
            "three_percent": "0.299",
            "two_attempts": 579,
            "two_fg": 286,
            "two_percent": "0.494"
        },
        {
            "AST": 71,
            "BLK": 53,
            "DRB": 181,
            "ORB": 53,
            "PF": 150,
            "PTS": 647,
            "STL": 41,
            "TOV": 93,
            "TRB": 234,
            "age": 21,
            "effect_fg_percent": "0.504",
            "field_attempts": 553,
            "field_goals": 244,
            "field_percent": "0.441",
            "ft": 90,
            "ft_percent": "0.643",
            "fta": 140,
            "games": 76,
            "games_started": 50,
            "id": 7888,
            "minutes_played": 1630,
            "player_name": "Dont\u00e9 Greene",
            "season": 2010,
            "team": "SAC",
            "three_attempts": 183,
            "three_fg": 69,
            "three_percent": "0.377",
            "two_attempts": 370,
            "two_fg": 175,
            "two_percent": "0.473"
        },
        {
            "AST": 75,
            "BLK": 26,
            "DRB": 190,
            "ORB": 32,
            "PF": 160,
            "PTS": 635,
            "STL": 32,
            "TOV": 67,
            "TRB": 222,
            "age": 30,
            "effect_fg_percent": "0.480",
            "field_attempts": 587,
            "field_goals": 234,
            "field_percent": "0.399",
            "ft": 71,
            "ft_percent": "0.717",
            "fta": 99,
            "games": 75,
            "games_started": 28,
            "id": 7889,
            "minutes_played": 1477,
            "player_name": "Andr\u00e9s Nocioni",
            "season": 2010,
            "team": "SAC",
            "three_attempts": 249,
            "three_fg": 96,
            "three_percent": "0.386",
            "two_attempts": 338,
            "two_fg": 138,
            "two_percent": "0.408"
        },
        {
            "AST": 26,
            "BLK": 17,
            "DRB": 116,
            "ORB": 66,
            "PF": 88,
            "PTS": 504,
            "STL": 27,
            "TOV": 50,
            "TRB": 182,
            "age": 26,
            "effect_fg_percent": "0.521",
            "field_attempts": 379,
            "field_goals": 197,
            "field_percent": "0.520",
            "ft": 109,
            "ft_percent": "0.741",
            "fta": 147,
            "games": 28,
            "games_started": 28,
            "id": 7890,
            "minutes_played": 1054,
            "player_name": "Carl Landry",
            "season": 2010,
            "team": "SAC",
            "three_attempts": 3,
            "three_fg": 1,
            "three_percent": "0.333",
            "two_attempts": 376,
            "two_fg": 196,
            "two_percent": "0.521"
        },
        {
            "AST": 58,
            "BLK": 6,
            "DRB": 140,
            "ORB": 51,
            "PF": 83,
            "PTS": 250,
            "STL": 34,
            "TOV": 42,
            "TRB": 191,
            "age": 32,
            "effect_fg_percent": "0.432",
            "field_attempts": 241,
            "field_goals": 91,
            "field_percent": "0.378",
            "ft": 42,
            "ft_percent": "0.737",
            "fta": 57,
            "games": 69,
            "games_started": 2,
            "id": 7891,
            "minutes_played": 944,
            "player_name": "Ime Udoka",
            "season": 2010,
            "team": "SAC",
            "three_attempts": 91,
            "three_fg": 26,
            "three_percent": "0.286",
            "two_attempts": 150,
            "two_fg": 65,
            "two_percent": "0.433"
        },
        {
            "AST": 57,
            "BLK": 4,
            "DRB": 74,
            "ORB": 20,
            "PF": 51,
            "PTS": 436,
            "STL": 23,
            "TOV": 35,
            "TRB": 94,
            "age": 26,
            "effect_fg_percent": "0.456",
            "field_attempts": 339,
            "field_goals": 135,
            "field_percent": "0.398",
            "ft": 127,
            "ft_percent": "0.819",
            "fta": 155,
            "games": 22,
            "games_started": 21,
            "id": 7892,
            "minutes_played": 774,
            "player_name": "Kevin Martin",
            "season": 2010,
            "team": "SAC",
            "three_attempts": 110,
            "three_fg": 39,
            "three_percent": "0.355",
            "two_attempts": 229,
            "two_fg": 96,
            "two_percent": "0.419"
        },
        {
            "AST": 22,
            "BLK": 5,
            "DRB": 108,
            "ORB": 105,
            "PF": 115,
            "PTS": 147,
            "STL": 15,
            "TOV": 23,
            "TRB": 213,
            "age": 22,
            "effect_fg_percent": "0.534",
            "field_attempts": 103,
            "field_goals": 55,
            "field_percent": "0.534",
            "ft": 37,
            "ft_percent": "0.597",
            "fta": 62,
            "games": 52,
            "games_started": 4,
            "id": 7893,
            "minutes_played": 654,
            "player_name": "Jon Brockman",
            "season": 2010,
            "team": "SAC",
            "three_attempts": 0,
            "three_fg": 0,
            "three_percent": null,
            "two_attempts": 103,
            "two_fg": 55,
            "two_percent": "0.534"
        },
        {
            "AST": 45,
            "BLK": 19,
            "DRB": 55,
            "ORB": 11,
            "PF": 49,
            "PTS": 202,
            "STL": 10,
            "TOV": 21,
            "TRB": 66,
            "age": 28,
            "effect_fg_percent": "0.531",
            "field_attempts": 176,
            "field_goals": 82,
            "field_percent": "0.466",
            "ft": 15,
            "ft_percent": "0.882",
            "fta": 17,
            "games": 25,
            "games_started": 4,
            "id": 7894,
            "minutes_played": 575,
            "player_name": "Francisco Garc\u00eda",
            "season": 2010,
            "team": "SAC",
            "three_attempts": 59,
            "three_fg": 23,
            "three_percent": "0.390",
            "two_attempts": 117,
            "two_fg": 59,
            "two_percent": "0.504"
        },
        {
            "AST": 121,
            "BLK": 3,
            "DRB": 35,
            "ORB": 15,
            "PF": 46,
            "PTS": 234,
            "STL": 29,
            "TOV": 59,
            "TRB": 50,
            "age": 23,
            "effect_fg_percent": "0.503",
            "field_attempts": 190,
            "field_goals": 88,
            "field_percent": "0.463",
            "ft": 43,
            "ft_percent": "0.694",
            "fta": 62,
            "games": 39,
            "games_started": 0,
            "id": 7895,
            "minutes_played": 517,
            "player_name": "Sergio Rodr\u00edguez",
            "season": 2010,
            "team": "SAC",
            "three_attempts": 42,
            "three_fg": 15,
            "three_percent": "0.357",
            "two_attempts": 148,
            "two_fg": 73,
            "two_percent": "0.493"
        },
        {
            "AST": 17,
            "BLK": 7,
            "DRB": 50,
            "ORB": 20,
            "PF": 46,
            "PTS": 123,
            "STL": 12,
            "TOV": 19,
            "TRB": 70,
            "age": 25,
            "effect_fg_percent": "0.459",
            "field_attempts": 111,
            "field_goals": 51,
            "field_percent": "0.459",
            "ft": 21,
            "ft_percent": "0.656",
            "fta": 32,
            "games": 37,
            "games_started": 4,
            "id": 7896,
            "minutes_played": 331,
            "player_name": "Sean May",
            "season": 2010,
            "team": "SAC",
            "three_attempts": 4,
            "three_fg": 0,
            "three_percent": "0.000",
            "two_attempts": 107,
            "two_fg": 51,
            "two_percent": "0.477"
        },
        {
            "AST": 15,
            "BLK": 10,
            "DRB": 51,
            "ORB": 35,
            "PF": 42,
            "PTS": 41,
            "STL": 10,
            "TOV": 17,
            "TRB": 86,
            "age": 32,
            "effect_fg_percent": "0.486",
            "field_attempts": 35,
            "field_goals": 17,
            "field_percent": "0.486",
            "ft": 7,
            "ft_percent": "0.583",
            "fta": 12,
            "games": 26,
            "games_started": 2,
            "id": 7897,
            "minutes_played": 313,
            "player_name": "Kenny Thomas",
            "season": 2010,
            "team": "SAC",
            "three_attempts": 0,
            "three_fg": 0,
            "three_percent": null,
            "two_attempts": 35,
            "two_fg": 17,
            "two_percent": "0.486"
        },
        {
            "AST": 3,
            "BLK": 1,
            "DRB": 12,
            "ORB": 6,
            "PF": 3,
            "PTS": 8,
            "STL": 1,
            "TOV": 7,
            "TRB": 18,
            "age": 24,
            "effect_fg_percent": "0.333",
            "field_attempts": 12,
            "field_goals": 4,
            "field_percent": "0.333",
            "ft": 0,
            "ft_percent": "0.000",
            "fta": 2,
            "games": 10,
            "games_started": 2,
            "id": 7898,
            "minutes_played": 67,
            "player_name": "Dominic McGuire",
            "season": 2010,
            "team": "SAC",
            "three_attempts": 0,
            "three_fg": 0,
            "three_percent": null,
            "two_attempts": 12,
            "two_fg": 4,
            "two_percent": "0.333"
        },
        {
            "AST": 2,
            "BLK": 1,
            "DRB": 9,
            "ORB": 4,
            "PF": 5,
            "PTS": 13,
            "STL": 1,
            "TOV": 4,
            "TRB": 13,
            "age": 32,
            "effect_fg_percent": "0.417",
            "field_attempts": 12,
            "field_goals": 5,
            "field_percent": "0.417",
            "ft": 3,
            "ft_percent": "0.750",
            "fta": 4,
            "games": 5,
            "games_started": 4,
            "id": 7899,
            "minutes_played": 66,
            "player_name": "Desmond Mason",
            "season": 2010,
            "team": "SAC",
            "three_attempts": 0,
            "three_fg": 0,
            "three_percent": null,
            "two_attempts": 12,
            "two_fg": 5,
            "two_percent": "0.417"
        },
        {
            "AST": 2,
            "BLK": 4,
            "DRB": 9,
            "ORB": 5,
            "PF": 5,
            "PTS": 10,
            "STL": 2,
            "TOV": 4,
            "TRB": 14,
            "age": 25,
            "effect_fg_percent": "0.333",
            "field_attempts": 12,
            "field_goals": 4,
            "field_percent": "0.333",
            "ft": 2,
            "ft_percent": "1.000",
            "fta": 2,
            "games": 6,
            "games_started": 0,
            "id": 7900,
            "minutes_played": 56,
            "player_name": "Hilton Armstrong",
            "season": 2010,
            "team": "SAC",
            "three_attempts": 0,
            "three_fg": 0,
            "three_percent": null,
            "two_attempts": 12,
            "two_fg": 4,
            "two_percent": "0.333"
        },
        {
            "AST": 0,
            "BLK": 1,
            "DRB": 13,
            "ORB": 5,
            "PF": 9,
            "PTS": 12,
            "STL": 1,
            "TOV": 2,
            "TRB": 18,
            "age": 26,
            "effect_fg_percent": "0.444",
            "field_attempts": 9,
            "field_goals": 4,
            "field_percent": "0.444",
            "ft": 4,
            "ft_percent": "0.400",
            "fta": 10,
            "games": 8,
            "games_started": 0,
            "id": 7901,
            "minutes_played": 52,
            "player_name": "Joey Dorsey",
            "season": 2010,
            "team": "SAC",
            "three_attempts": 0,
            "three_fg": 0,
            "three_percent": null,
            "two_attempts": 9,
            "two_fg": 4,
            "two_percent": "0.444"
        },
        {
            "AST": 2,
            "BLK": 0,
            "DRB": 2,
            "ORB": 1,
            "PF": 1,
            "PTS": 11,
            "STL": 1,
            "TOV": 2,
            "TRB": 3,
            "age": 23,
            "effect_fg_percent": "0.375",
            "field_attempts": 8,
            "field_goals": 3,
            "field_percent": "0.375",
            "ft": 5,
            "ft_percent": "1.000",
            "fta": 5,
            "games": 5,
            "games_started": 0,
            "id": 7902,
            "minutes_played": 23,
            "player_name": "Garrett Temple",
            "season": 2010,
            "team": "SAC",
            "three_attempts": 2,
            "three_fg": 0,
            "three_percent": "0.000",
            "two_attempts": 6,
            "two_fg": 3,
            "two_percent": "0.500"
        },
        {
            "AST": 82,
            "BLK": 83,
            "DRB": 502,
            "ORB": 230,
            "PF": 281,
            "PTS": 1896,
            "STL": 52,
            "TOV": 213,
            "TRB": 732,
            "age": 27,
            "effect_fg_percent": "0.557",
            "field_attempts": 1264,
            "field_goals": 704,
            "field_percent": "0.557",
            "ft": 487,
            "ft_percent": "0.771",
            "fta": 632,
            "games": 82,
            "games_started": 82,
            "id": 7903,
            "minutes_played": 2838,
            "player_name": "Amar'e Stoudemire",
            "season": 2010,
            "team": "PHO",
            "three_attempts": 6,
            "three_fg": 1,
            "three_percent": "0.167",
            "two_attempts": 1258,
            "two_fg": 703,
            "two_percent": "0.559"
        },
        {
            "AST": 892,
            "BLK": 12,
            "DRB": 234,
            "ORB": 34,
            "PF": 108,
            "PTS": 1333,
            "STL": 42,
            "TOV": 295,
            "TRB": 268,
            "age": 35,
            "effect_fg_percent": "0.570",
            "field_attempts": 985,
            "field_goals": 499,
            "field_percent": "0.507",
            "ft": 211,
            "ft_percent": "0.938",
            "fta": 225,
            "games": 81,
            "games_started": 81,
            "id": 7904,
            "minutes_played": 2660,
            "player_name": "Steve Nash",
            "season": 2010,
            "team": "PHO",
            "three_attempts": 291,
            "three_fg": 124,
            "three_percent": "0.426",
            "two_attempts": 694,
            "two_fg": 375,
            "two_percent": "0.540"
        },
        {
            "AST": 143,
            "BLK": 33,
            "DRB": 323,
            "ORB": 81,
            "PF": 169,
            "PTS": 1239,
            "STL": 66,
            "TOV": 92,
            "TRB": 404,
            "age": 29,
            "effect_fg_percent": "0.553",
            "field_attempts": 998,
            "field_goals": 473,
            "field_percent": "0.474",
            "ft": 136,
            "ft_percent": "0.739",
            "fta": 184,
            "games": 79,
            "games_started": 76,
            "id": 7905,
            "minutes_played": 2485,
            "player_name": "Jason Richardson",
            "season": 2010,
            "team": "PHO",
            "three_attempts": 400,
            "three_fg": 157,
            "three_percent": "0.393",
            "two_attempts": 598,
            "two_fg": 316,
            "two_percent": "0.528"
        },
        {
            "AST": 193,
            "BLK": 36,
            "DRB": 371,
            "ORB": 74,
            "PF": 165,
            "PTS": 912,
            "STL": 60,
            "TOV": 108,
            "TRB": 445,
            "age": 37,
            "effect_fg_percent": "0.503",
            "field_attempts": 703,
            "field_goals": 336,
            "field_percent": "0.478",
            "ft": 205,
            "ft_percent": "0.817",
            "fta": 251,
            "games": 81,
            "games_started": 81,
            "id": 7906,
            "minutes_played": 2430,
            "player_name": "Grant Hill",
            "season": 2010,
            "team": "PHO",
            "three_attempts": 80,
            "three_fg": 35,
            "three_percent": "0.438",
            "two_attempts": 623,
            "two_fg": 301,
            "two_percent": "0.483"
        },
        {
            "AST": 113,
            "BLK": 74,
            "DRB": 361,
            "ORB": 66,
            "PF": 263,
            "PTS": 904,
            "STL": 64,
            "TOV": 73,
            "TRB": 427,
            "age": 26,
            "effect_fg_percent": "0.573",
            "field_attempts": 703,
            "field_goals": 317,
            "field_percent": "0.451",
            "ft": 98,
            "ft_percent": "0.810",
            "fta": 121,
            "games": 81,
            "games_started": 41,
            "id": 7907,
            "minutes_played": 2190,
            "player_name": "Channing Frye",
            "season": 2010,
            "team": "PHO",
            "three_attempts": 392,
            "three_fg": 172,
            "three_percent": "0.439",
            "two_attempts": 311,
            "two_fg": 145,
            "two_percent": "0.466"
        },
        {
            "AST": 115,
            "BLK": 16,
            "DRB": 182,
            "ORB": 99,
            "PF": 162,
            "PTS": 674,
            "STL": 81,
            "TOV": 68,
            "TRB": 281,
            "age": 24,
            "effect_fg_percent": "0.582",
            "field_attempts": 490,
            "field_goals": 225,
            "field_percent": "0.459",
            "ft": 104,
            "ft_percent": "0.754",
            "fta": 138,
            "games": 82,
            "games_started": 1,
            "id": 7908,
            "minutes_played": 1991,
            "player_name": "Jared Dudley",
            "season": 2010,
            "team": "PHO",
            "three_attempts": 262,
            "three_fg": 120,
            "three_percent": "0.458",
            "two_attempts": 228,
            "two_fg": 105,
            "two_percent": "0.461"
        },
        {
            "AST": 241,
            "BLK": 8,
            "DRB": 133,
            "ORB": 38,
            "PF": 131,
            "PTS": 635,
            "STL": 48,
            "TOV": 126,
            "TRB": 171,
            "age": 23,
            "effect_fg_percent": "0.527",
            "field_attempts": 491,
            "field_goals": 222,
            "field_percent": "0.452",
            "ft": 117,
            "ft_percent": "0.736",
            "fta": 159,
            "games": 80,
            "games_started": 2,
            "id": 7909,
            "minutes_played": 1442,
            "player_name": "Goran Dragi\u0107",
            "season": 2010,
            "team": "PHO",
            "three_attempts": 188,
            "three_fg": 74,
            "three_percent": "0.394",
            "two_attempts": 303,
            "two_fg": 148,
            "two_percent": "0.488"
        },
        {
            "AST": 31,
            "BLK": 73,
            "DRB": 218,
            "ORB": 128,
            "PF": 169,
            "PTS": 371,
            "STL": 24,
            "TOV": 57,
            "TRB": 346,
            "age": 27,
            "effect_fg_percent": "0.551",
            "field_attempts": 276,
            "field_goals": 152,
            "field_percent": "0.551",
            "ft": 67,
            "ft_percent": "0.545",
            "fta": 123,
            "games": 79,
            "games_started": 0,
            "id": 7910,
            "minutes_played": 1168,
            "player_name": "Lou Amundson",
            "season": 2010,
            "team": "PHO",
            "three_attempts": 1,
            "three_fg": 0,
            "three_percent": "0.000",
            "two_attempts": 275,
            "two_fg": 152,
            "two_percent": "0.553"
        },
        {
            "AST": 7,
            "BLK": 53,
            "DRB": 144,
            "ORB": 104,
            "PF": 117,
            "PTS": 430,
            "STL": 10,
            "TOV": 41,
            "TRB": 248,
            "age": 21,
            "effect_fg_percent": "0.588",
            "field_attempts": 291,
            "field_goals": 171,
            "field_percent": "0.588",
            "ft": 88,
            "ft_percent": "0.704",
            "fta": 125,
            "games": 51,
            "games_started": 31,
            "id": 7911,
            "minutes_played": 986,
            "player_name": "Robin Lopez",
            "season": 2010,
            "team": "PHO",
            "three_attempts": 0,
            "three_fg": 0,
            "three_percent": null,
            "two_attempts": 291,
            "two_fg": 171,
            "two_percent": "0.588"
        },
        {
            "AST": 64,
            "BLK": 12,
            "DRB": 58,
            "ORB": 11,
            "PF": 71,
            "PTS": 418,
            "STL": 23,
            "TOV": 46,
            "TRB": 69,
            "age": 27,
            "effect_fg_percent": "0.485",
            "field_attempts": 365,
            "field_goals": 155,
            "field_percent": "0.425",
            "ft": 64,
            "ft_percent": "0.877",
            "fta": 73,
            "games": 44,
            "games_started": 5,
            "id": 7912,
            "minutes_played": 786,
            "player_name": "Leandro Barbosa",
            "season": 2010,
            "team": "PHO",
            "three_attempts": 136,
            "three_fg": 44,
            "three_percent": "0.324",
            "two_attempts": 229,
            "two_fg": 111,
            "two_percent": "0.485"
        },
        {
            "AST": 21,
            "BLK": 13,
            "DRB": 44,
            "ORB": 18,
            "PF": 25,
            "PTS": 140,
            "STL": 7,
            "TOV": 23,
            "TRB": 62,
            "age": 22,
            "effect_fg_percent": "0.377",
            "field_attempts": 151,
            "field_goals": 56,
            "field_percent": "0.371",
            "ft": 26,
            "ft_percent": "0.722",
            "fta": 36,
            "games": 51,
            "games_started": 0,
            "id": 7913,
            "minutes_played": 383,
            "player_name": "Earl Clark",
            "season": 2010,
            "team": "PHO",
            "three_attempts": 5,
            "three_fg": 2,
            "three_percent": "0.400",
            "two_attempts": 146,
            "two_fg": 54,
            "two_percent": "0.370"
        },
        {
            "AST": 6,
            "BLK": 3,
            "DRB": 40,
            "ORB": 22,
            "PF": 42,
            "PTS": 34,
            "STL": 2,
            "TOV": 10,
            "TRB": 62,
            "age": 31,
            "effect_fg_percent": "0.387",
            "field_attempts": 31,
            "field_goals": 12,
            "field_percent": "0.387",
            "ft": 10,
            "ft_percent": "0.400",
            "fta": 25,
            "games": 34,
            "games_started": 10,
            "id": 7914,
            "minutes_played": 261,
            "player_name": "Jarron Collins",
            "season": 2010,
            "team": "PHO",
            "three_attempts": 0,
            "three_fg": 0,
            "three_percent": null,
            "two_attempts": 31,
            "two_fg": 12,
            "two_percent": "0.387"
        },
        {
            "AST": 3,
            "BLK": 0,
            "DRB": 2,
            "ORB": 5,
            "PF": 5,
            "PTS": 43,
            "STL": 0,
            "TOV": 4,
            "TRB": 7,
            "age": 25,
            "effect_fg_percent": "0.450",
            "field_attempts": 30,
            "field_goals": 13,
            "field_percent": "0.433",
            "ft": 16,
            "ft_percent": "0.762",
            "fta": 21,
            "games": 11,
            "games_started": 0,
            "id": 7915,
            "minutes_played": 71,
            "player_name": "Alando Tucker",
            "season": 2010,
            "team": "PHO",
            "three_attempts": 7,
            "three_fg": 1,
            "three_percent": "0.143",
            "two_attempts": 23,
            "two_fg": 12,
            "two_percent": "0.522"
        },
        {
            "AST": 1,
            "BLK": 2,
            "DRB": 2,
            "ORB": 0,
            "PF": 4,
            "PTS": 10,
            "STL": 0,
            "TOV": 1,
            "TRB": 2,
            "age": 23,
            "effect_fg_percent": "0.400",
            "field_attempts": 10,
            "field_goals": 4,
            "field_percent": "0.400",
            "ft": 2,
            "ft_percent": "0.500",
            "fta": 4,
            "games": 8,
            "games_started": 0,
            "id": 7916,
            "minutes_played": 32,
            "player_name": "Taylor Griffin",
            "season": 2010,
            "team": "PHO",
            "three_attempts": 2,
            "three_fg": 0,
            "three_percent": "0.000",
            "two_attempts": 8,
            "two_fg": 4,
            "two_percent": "0.500"
        },
        {
            "AST": 0,
            "BLK": 0,
            "DRB": 2,
            "ORB": 0,
            "PF": 1,
            "PTS": 0,
            "STL": 0,
            "TOV": 0,
            "TRB": 2,
            "age": 26,
            "effect_fg_percent": null,
            "field_attempts": 0,
            "field_goals": 0,
            "field_percent": null,
            "ft": 0,
            "ft_percent": null,
            "fta": 0,
            "games": 2,
            "games_started": 0,
            "id": 7917,
            "minutes_played": 7,
            "player_name": "Dwayne Jones",
            "season": 2010,
            "team": "PHO",
            "three_attempts": 0,
            "three_fg": 0,
            "three_percent": null,
            "two_attempts": 0,
            "two_fg": 0,
            "two_percent": null
        },
        {
            "AST": 472,
            "BLK": 19,
            "DRB": 308,
            "ORB": 48,
            "PF": 252,
            "PTS": 1399,
            "STL": 152,
            "TOV": 243,
            "TRB": 356,
            "age": 21,
            "effect_fg_percent": "0.535",
            "field_attempts": 1143,
            "field_goals": 528,
            "field_percent": "0.462",
            "ft": 177,
            "ft_percent": "0.885",
            "fta": 200,
            "games": 80,
            "games_started": 77,
            "id": 7918,
            "minutes_played": 2896,
            "player_name": "Stephen Curry",
            "season": 2010,
            "team": "GSW",
            "three_attempts": 380,
            "three_fg": 166,
            "three_percent": "0.437",
            "two_attempts": 763,
            "two_fg": 362,
            "two_percent": "0.474"
        },
        {
            "AST": 340,
            "BLK": 25,
            "DRB": 210,
            "ORB": 47,
            "PF": 189,
            "PTS": 1631,
            "STL": 143,
            "TOV": 244,
            "TRB": 257,
            "age": 24,
            "effect_fg_percent": "0.476",
            "field_attempts": 1406,
            "field_goals": 631,
            "field_percent": "0.449",
            "ft": 292,
            "ft_percent": "0.753",
            "fta": 388,
            "games": 64,
            "games_started": 64,
            "id": 7919,
            "minutes_played": 2647,
            "player_name": "Monta Ellis",
            "season": 2010,
            "team": "GSW",
            "three_attempts": 228,
            "three_fg": 77,
            "three_percent": "0.338",
            "two_attempts": 1178,
            "two_fg": 554,
            "two_percent": "0.470"
        },
        {
            "AST": 172,
            "BLK": 4,
            "DRB": 281,
            "ORB": 92,
            "PF": 231,
            "PTS": 1387,
            "STL": 51,
            "TOV": 168,
            "TRB": 373,
            "age": 30,
            "effect_fg_percent": "0.523",
            "field_attempts": 886,
            "field_goals": 457,
            "field_percent": "0.516",
            "ft": 460,
            "ft_percent": "0.835",
            "fta": 551,
            "games": 70,
            "games_started": 49,
            "id": 7920,
            "minutes_played": 2081,
            "player_name": "Corey Maggette",
            "season": 2010,
            "team": "GSW",
            "three_attempts": 50,
            "three_fg": 13,
            "three_percent": "0.260",
            "two_attempts": 836,
            "two_fg": 444,
            "two_percent": "0.531"
        },
        {
            "AST": 104,
            "BLK": 16,
            "DRB": 198,
            "ORB": 61,
            "PF": 158,
            "PTS": 899,
            "STL": 65,
            "TOV": 84,
            "TRB": 259,
            "age": 24,
            "effect_fg_percent": "0.568",
            "field_attempts": 703,
            "field_goals": 329,
            "field_percent": "0.468",
            "ft": 101,
            "ft_percent": "0.886",
            "fta": 114,
            "games": 69,
            "games_started": 37,
            "id": 7921,
            "minutes_played": 2018,
            "player_name": "Anthony Morrow",
            "season": 2010,
            "team": "GSW",
            "three_attempts": 307,
            "three_fg": 140,
            "three_percent": "0.456",
            "two_attempts": 396,
            "two_fg": 189,
            "two_percent": "0.477"
        },
        {
            "AST": 180,
            "BLK": 8,
            "DRB": 141,
            "ORB": 28,
            "PF": 124,
            "PTS": 667,
            "STL": 103,
            "TOV": 69,
            "TRB": 169,
            "age": 25,
            "effect_fg_percent": "0.510",
            "field_attempts": 528,
            "field_goals": 247,
            "field_percent": "0.468",
            "ft": 128,
            "ft_percent": "0.771",
            "fta": 166,
            "games": 65,
            "games_started": 15,
            "id": 7922,
            "minutes_played": 1788,
            "player_name": "C.J. Watson",
            "season": 2010,
            "team": "GSW",
            "three_attempts": 145,
            "three_fg": 45,
            "three_percent": "0.310",
            "two_attempts": 383,
            "two_fg": 202,
            "two_percent": "0.527"
        },
        {
            "AST": 87,
            "BLK": 33,
            "DRB": 235,
            "ORB": 84,
            "PF": 127,
            "PTS": 539,
            "STL": 32,
            "TOV": 46,
            "TRB": 319,
            "age": 24,
            "effect_fg_percent": "0.487",
            "field_attempts": 448,
            "field_goals": 193,
            "field_percent": "0.431",
            "ft": 103,
            "ft_percent": "0.769",
            "fta": 134,
            "games": 44,
            "games_started": 29,
            "id": 7923,
            "minutes_played": 1423,
            "player_name": "Anthony Tolliver",
            "season": 2010,
            "team": "GSW",
            "three_attempts": 151,
            "three_fg": 50,
            "three_percent": "0.331",
            "two_attempts": 297,
            "two_fg": 143,
            "two_percent": "0.481"
        },
        {
            "AST": 90,
            "BLK": 54,
            "DRB": 137,
            "ORB": 54,
            "PF": 98,
            "PTS": 207,
            "STL": 23,
            "TOV": 49,
            "TRB": 191,
            "age": 27,
            "effect_fg_percent": "0.582",
            "field_attempts": 146,
            "field_goals": 85,
            "field_percent": "0.582",
            "ft": 37,
            "ft_percent": "0.474",
            "fta": 78,
            "games": 42,
            "games_started": 20,
            "id": 7924,
            "minutes_played": 872,
            "player_name": "Ronny Turiaf",
            "season": 2010,
            "team": "GSW",
            "three_attempts": 1,
            "three_fg": 0,
            "three_percent": "0.000",
            "two_attempts": 145,
            "two_fg": 85,
            "two_percent": "0.586"
        },
        {
            "AST": 37,
            "BLK": 35,
            "DRB": 111,
            "ORB": 56,
            "PF": 132,
            "PTS": 270,
            "STL": 13,
            "TOV": 30,
            "TRB": 167,
            "age": 25,
            "effect_fg_percent": "0.502",
            "field_attempts": 217,
            "field_goals": 109,
            "field_percent": "0.502",
            "ft": 52,
            "ft_percent": "0.754",
            "fta": 69,
            "games": 60,
            "games_started": 9,
            "id": 7925,
            "minutes_played": 783,
            "player_name": "Chris Hunter",
            "season": 2010,
            "team": "GSW",
            "three_attempts": 4,
            "three_fg": 0,
            "three_percent": "0.000",
            "two_attempts": 213,
            "two_fg": 109,
            "two_percent": "0.512"
        },
        {
            "AST": 66,
            "BLK": 6,
            "DRB": 92,
            "ORB": 18,
            "PF": 49,
            "PTS": 365,
            "STL": 23,
            "TOV": 29,
            "TRB": 110,
            "age": 23,
            "effect_fg_percent": "0.553",
            "field_attempts": 283,
            "field_goals": 140,
            "field_percent": "0.495",
            "ft": 52,
            "ft_percent": "0.839",
            "fta": 62,
            "games": 24,
            "games_started": 10,
            "id": 7926,
            "minutes_played": 782,
            "player_name": "Reggie Williams",
            "season": 2010,
            "team": "GSW",
            "three_attempts": 92,
            "three_fg": 33,
            "three_percent": "0.359",
            "two_attempts": 191,
            "two_fg": 107,
            "two_percent": "0.560"
        },
        {
            "AST": 57,
            "BLK": 44,
            "DRB": 196,
            "ORB": 63,
            "PF": 117,
            "PTS": 166,
            "STL": 20,
            "TOV": 32,
            "TRB": 259,
            "age": 23,
            "effect_fg_percent": "0.591",
            "field_attempts": 137,
            "field_goals": 81,
            "field_percent": "0.591",
            "ft": 4,
            "ft_percent": "0.160",
            "fta": 25,
            "games": 33,
            "games_started": 29,
            "id": 7927,
            "minutes_played": 763,
            "player_name": "Andris Biedri\u0146\u0161",
            "season": 2010,
            "team": "GSW",
            "three_attempts": 0,
            "three_fg": 0,
            "three_percent": null,
            "two_attempts": 137,
            "two_fg": 81,
            "two_percent": "0.591"
        },
        {
            "AST": 32,
            "BLK": 10,
            "DRB": 93,
            "ORB": 21,
            "PF": 89,
            "PTS": 242,
            "STL": 41,
            "TOV": 15,
            "TRB": 114,
            "age": 32,
            "effect_fg_percent": "0.549",
            "field_attempts": 206,
            "field_goals": 89,
            "field_percent": "0.432",
            "ft": 16,
            "ft_percent": "0.696",
            "fta": 23,
            "games": 45,
            "games_started": 4,
            "id": 7928,
            "minutes_played": 761,
            "player_name": "Devean George",
            "season": 2010,
            "team": "GSW",
            "three_attempts": 123,
            "three_fg": 48,
            "three_percent": "0.390",
            "two_attempts": 83,
            "two_fg": 41,
            "two_percent": "0.494"
        },
        {
            "AST": 38,
            "BLK": 6,
            "DRB": 106,
            "ORB": 43,
            "PF": 79,
            "PTS": 217,
            "STL": 26,
            "TOV": 39,
            "TRB": 149,
            "age": 29,
            "effect_fg_percent": "0.435",
            "field_attempts": 231,
            "field_goals": 89,
            "field_percent": "0.385",
            "ft": 16,
            "ft_percent": "0.762",
            "fta": 21,
            "games": 33,
            "games_started": 20,
            "id": 7929,
            "minutes_played": 758,
            "player_name": "Vladimir Radmanovi\u0107",
            "season": 2010,
            "team": "GSW",
            "three_attempts": 86,
            "three_fg": 23,
            "three_percent": "0.267",
            "two_attempts": 145,
            "two_fg": 66,
            "two_percent": "0.455"
        },
        {
            "AST": 42,
            "BLK": 51,
            "DRB": 142,
            "ORB": 73,
            "PF": 92,
            "PTS": 384,
            "STL": 28,
            "TOV": 49,
            "TRB": 215,
            "age": 20,
            "effect_fg_percent": "0.445",
            "field_attempts": 309,
            "field_goals": 137,
            "field_percent": "0.443",
            "ft": 109,
            "ft_percent": "0.801",
            "fta": 136,
            "games": 33,
            "games_started": 8,
            "id": 7930,
            "minutes_played": 749,
            "player_name": "Anthony Randolph",
            "season": 2010,
            "team": "GSW",
            "three_attempts": 5,
            "three_fg": 1,
            "three_percent": "0.200",
            "two_attempts": 304,
            "two_fg": 136,
            "two_percent": "0.447"
        },
        {
            "AST": 36,
            "BLK": 13,
            "DRB": 43,
            "ORB": 26,
            "PF": 60,
            "PTS": 115,
            "STL": 5,
            "TOV": 21,
            "TRB": 69,
            "age": 34,
            "effect_fg_percent": "0.600",
            "field_attempts": 90,
            "field_goals": 54,
            "field_percent": "0.600",
            "ft": 7,
            "ft_percent": "0.636",
            "fta": 11,
            "games": 23,
            "games_started": 20,
            "id": 7931,
            "minutes_played": 406,
            "player_name": "Mikki Moore",
            "season": 2010,
            "team": "GSW",
            "three_attempts": 0,
            "three_fg": 0,
            "three_percent": null,
            "two_attempts": 90,
            "two_fg": 54,
            "two_percent": "0.600"
        },
        {
            "AST": 42,
            "BLK": 6,
            "DRB": 29,
            "ORB": 6,
            "PF": 16,
            "PTS": 149,
            "STL": 14,
            "TOV": 26,
            "TRB": 35,
            "age": 31,
            "effect_fg_percent": "0.462",
            "field_attempts": 133,
            "field_goals": 56,
            "field_percent": "0.421",
            "ft": 26,
            "ft_percent": "0.703",
            "fta": 37,
            "games": 9,
            "games_started": 9,
            "id": 7932,
            "minutes_played": 300,
            "player_name": "Stephen Jackson",
            "season": 2010,
            "team": "GSW",
            "three_attempts": 40,
            "three_fg": 11,
            "three_percent": "0.275",
            "two_attempts": 93,
            "two_fg": 45,
            "two_percent": "0.484"
        },
        {
            "AST": 9,
            "BLK": 0,
            "DRB": 30,
            "ORB": 17,
            "PF": 36,
            "PTS": 90,
            "STL": 8,
            "TOV": 13,
            "TRB": 47,
            "age": 25,
            "effect_fg_percent": "0.420",
            "field_attempts": 88,
            "field_goals": 32,
            "field_percent": "0.364",
            "ft": 16,
            "ft_percent": "0.762",
            "fta": 21,
            "games": 10,
            "games_started": 2,
            "id": 7933,
            "minutes_played": 276,
            "player_name": "Cartier Martin",
            "season": 2010,
            "team": "GSW",
            "three_attempts": 31,
            "three_fg": 10,
            "three_percent": "0.323",
            "two_attempts": 57,
            "two_fg": 22,
            "two_percent": "0.386"
        },
        {
            "AST": 10,
            "BLK": 9,
            "DRB": 29,
            "ORB": 12,
            "PF": 16,
            "PTS": 125,
            "STL": 5,
            "TOV": 7,
            "TRB": 41,
            "age": 26,
            "effect_fg_percent": "0.602",
            "field_attempts": 88,
            "field_goals": 48,
            "field_percent": "0.545",
            "ft": 19,
            "ft_percent": "0.679",
            "fta": 28,
            "games": 9,
            "games_started": 7,
            "id": 7934,
            "minutes_played": 231,
            "player_name": "Kelenna Azubuike",
            "season": 2010,
            "team": "GSW",
            "three_attempts": 27,
            "three_fg": 10,
            "three_percent": "0.370",
            "two_attempts": 61,
            "two_fg": 38,
            "two_percent": "0.623"
        },
        {
            "AST": 15,
            "BLK": 1,
            "DRB": 12,
            "ORB": 4,
            "PF": 14,
            "PTS": 28,
            "STL": 3,
            "TOV": 6,
            "TRB": 16,
            "age": 26,
            "effect_fg_percent": "0.375",
            "field_attempts": 32,
            "field_goals": 11,
            "field_percent": "0.344",
            "ft": 4,
            "ft_percent": "0.667",
            "fta": 6,
            "games": 4,
            "games_started": 1,
            "id": 7935,
            "minutes_played": 108,
            "player_name": "Coby Karl",
            "season": 2010,
            "team": "GSW",
            "three_attempts": 11,
            "three_fg": 2,
            "three_percent": "0.182",
            "two_attempts": 21,
            "two_fg": 9,
            "two_percent": "0.429"
        },
        {
            "AST": 7,
            "BLK": 0,
            "DRB": 2,
            "ORB": 0,
            "PF": 5,
            "PTS": 31,
            "STL": 6,
            "TOV": 2,
            "TRB": 2,
            "age": 25,
            "effect_fg_percent": "0.679",
            "field_attempts": 14,
            "field_goals": 9,
            "field_percent": "0.643",
            "ft": 12,
            "ft_percent": "0.800",
            "fta": 15,
            "games": 5,
            "games_started": 0,
            "id": 7936,
            "minutes_played": 66,
            "player_name": "Acie Law",
            "season": 2010,
            "team": "GSW",
            "three_attempts": 3,
            "three_fg": 1,
            "three_percent": "0.333",
            "two_attempts": 11,
            "two_fg": 8,
            "two_percent": "0.727"
        },
        {
            "AST": 3,
            "BLK": 0,
            "DRB": 2,
            "ORB": 0,
            "PF": 2,
            "PTS": 11,
            "STL": 0,
            "TOV": 0,
            "TRB": 2,
            "age": 33,
            "effect_fg_percent": "0.917",
            "field_attempts": 6,
            "field_goals": 4,
            "field_percent": "0.667",
            "ft": 0,
            "ft_percent": null,
            "fta": 0,
            "games": 1,
            "games_started": 0,
            "id": 7937,
            "minutes_played": 23,
            "player_name": "Raja Bell",
            "season": 2010,
            "team": "GSW",
            "three_attempts": 3,
            "three_fg": 3,
            "three_percent": "1.000",
            "two_attempts": 3,
            "two_fg": 1,
            "two_percent": "0.333"
        },
        {
            "AST": 116,
            "BLK": 68,
            "DRB": 201,
            "ORB": 39,
            "PF": 121,
            "PTS": 979,
            "STL": 36,
            "TOV": 79,
            "TRB": 240,
            "age": 30,
            "effect_fg_percent": "0.493",
            "field_attempts": 870,
            "field_goals": 356,
            "field_percent": "0.409",
            "ft": 122,
            "ft_percent": "0.841",
            "fta": 145,
            "games": 82,
            "games_started": 64,
            "id": 7938,
            "minutes_played": 2702,
            "player_name": "Rasual Butler",
            "season": 2010,
            "team": "LAC",
            "three_attempts": 432,
            "three_fg": 145,
            "three_percent": "0.336",
            "two_attempts": 438,
            "two_fg": 211,
            "two_percent": "0.482"
        },
        {
            "AST": 120,
            "BLK": 94,
            "DRB": 520,
            "ORB": 184,
            "PF": 213,
            "PTS": 1408,
            "STL": 37,
            "TOV": 223,
            "TRB": 704,
            "age": 27,
            "effect_fg_percent": "0.490",
            "field_attempts": 1202,
            "field_goals": 589,
            "field_percent": "0.490",
            "ft": 230,
            "ft_percent": "0.749",
            "fta": 307,
            "games": 76,
            "games_started": 76,
            "id": 7939,
            "minutes_played": 2608,
            "player_name": "Chris Kaman",
            "season": 2010,
            "team": "LAC",
            "three_attempts": 6,
            "three_fg": 0,
            "three_percent": "0.000",
            "two_attempts": 1196,
            "two_fg": 589,
            "two_percent": "0.492"
        },
        {
            "AST": 598,
            "BLK": 43,
            "DRB": 214,
            "ORB": 52,
            "PF": 210,
            "PTS": 1145,
            "STL": 126,
            "TOV": 211,
            "TRB": 266,
            "age": 30,
            "effect_fg_percent": "0.446",
            "field_attempts": 1015,
            "field_goals": 412,
            "field_percent": "0.406",
            "ft": 239,
            "ft_percent": "0.821",
            "fta": 291,
            "games": 75,
            "games_started": 73,
            "id": 7940,
            "minutes_played": 2523,
            "player_name": "Baron Davis",
            "season": 2010,
            "team": "LAC",
            "three_attempts": 296,
            "three_fg": 82,
            "three_percent": "0.277",
            "two_attempts": 719,
            "two_fg": 330,
            "two_percent": "0.459"
        },
        {
            "AST": 186,
            "BLK": 14,
            "DRB": 135,
            "ORB": 25,
            "PF": 96,
            "PTS": 1045,
            "STL": 69,
            "TOV": 144,
            "TRB": 160,
            "age": 21,
            "effect_fg_percent": "0.525",
            "field_attempts": 784,
            "field_goals": 352,
            "field_percent": "0.449",
            "ft": 222,
            "ft_percent": "0.742",
            "fta": 299,
            "games": 62,
            "games_started": 60,
            "id": 7941,
            "minutes_played": 2229,
            "player_name": "Eric Gordon",
            "season": 2010,
            "team": "LAC",
            "three_attempts": 321,
            "three_fg": 119,
            "three_percent": "0.371",
            "two_attempts": 463,
            "two_fg": 233,
            "two_percent": "0.503"
        }
    ]
}